loyalicos/__init__.py
loyalicos/__version__.py
loyalicos/exceptions.py
loyalicos/interface.py
loyalicos/loyalicos.py
loyalicos/simplified_http_client.py
loyalicos-0.0.4.dist-info/LICENSE
loyalicos-0.0.4.dist-info/METADATA
loyalicos-0.0.4.dist-info/WHEEL
loyalicos-0.0.4.dist-info/top_level.txt
loyalicos-0.0.4.dist-info/RECORD
