Metadata-Version: 2.1
Name: loyalicos
Version: 0.0.4
Summary: SDK for easy integration with Loyalicos API
Home-page: https://github.com/loyalicos/python-sdk
Author: Alex Sánchez Vega
Author-email: alex@loyalicos.com
License: UNKNOWN
Project-URL: Bug Tracker, https://github.com/loyalicos/python-sdk/issues
Platform: UNKNOWN
Classifier: Programming Language :: Python :: 3
Classifier: License :: OSI Approved :: MIT License
Classifier: Operating System :: OS Independent
Requires-Python: >=3.8
License-File: LICENSE
Requires-Dist: requests
